setup.py
in_states/__init__.py
in_states/admin.py
in_states/apps.py
in_states/fields.py
in_states/forms.py
in_states/models.py
in_states/states.py
in_states/tests.py
in_states/views.py
in_states/migrations/__init__.py
vaishnavi_in_states/__init__.py
vaishnavi_in_states/asgi.py
vaishnavi_in_states/settings.py
vaishnavi_in_states/urls.py
vaishnavi_in_states/wsgi.py
vaishnavi_in_states.egg-info/PKG-INFO
vaishnavi_in_states.egg-info/SOURCES.txt
vaishnavi_in_states.egg-info/dependency_links.txt
vaishnavi_in_states.egg-info/requires.txt
vaishnavi_in_states.egg-info/top_level.txt